altair_catplot/__init__.py
altair_catplot/box.py
altair_catplot/catplot.py
altair_catplot/ecdf.py
altair_catplot/jitter.py
altair_catplot/jitterbox.py
altair_catplot/utils.py
altair_catplot-0.0.5.dist-info/LICENSE
altair_catplot-0.0.5.dist-info/METADATA
altair_catplot-0.0.5.dist-info/WHEEL
altair_catplot-0.0.5.dist-info/top_level.txt
altair_catplot-0.0.5.dist-info/RECORD
