Metadata-Version: 2.1
Name: altair-catplot
Version: 0.0.5
Summary: Utility to generate plots with categorical variables using Altair.
Home-page: https://github.com/justinbois/altair-catplot
Author: Justin Bois
Author-email: bois@caltech.edu
License: BSD
Download-URL: https://github.com/justinbois/altair-catplot/tarball/0.0.5
Platform: UNKNOWN
Classifier: Development Status :: 3 - Alpha
Classifier: Intended Audience :: Developers
Classifier: Programming Language :: Python :: 3
Requires-Dist: numpy
Requires-Dist: pandas
Requires-Dist: altair
